{
    "CPMultipliers": [
        0.094,
        0.13513743215803847,
        0.16639787,
        0.19265091454861796,
        0.21573247,
        0.23657265541932715,
        0.25572005,
        0.27353037931097973,
        0.29024988,
        0.30605738000722543,
        0.3210876,
        0.3354450348019347,
        0.34921268,
        0.36245775711118555,
        0.3752356,
        0.3875924191428145,
        0.39956728,
        0.4111935439951595,
        0.4225,
        0.4329264087965774,
        0.44310755,
        0.4530599628689135,
        0.4627984,
        0.4723360827308573,
        0.48168495,
        0.49085580932476297,
        0.49985844,
        0.5087017591555174,
        0.51739395,
        0.5259424956328841,
        0.5343543,
        0.5426357508963908,
        0.5507927,
        0.5588305922386229,
        0.5667545,
        0.574569134506658,
        0.5822789,
        0.5898879034974399,
        0.5974,
        0.6048236602280411,
        0.6121573,
        0.6194041050661919,
        0.6265671,
        0.6336491667895227,
        0.64065295,
        0.6475809587060136,
        0.65443563,
        0.6612192609753201,
        0.667934,
        0.6745818887829742,
        0.6811649,
        0.6876848943474521,
        0.69414365,
        0.7005428891384746,
        0.7068842,
        0.713169102419072,
        0.7193991,
        0.7255756180718899,
        0.7317,
        0.7347410173422504,
        0.7377695,
        0.7407855800803546,
        0.74378943,
        0.7467812039953893,
        0.74976104,
        0.7527290986842915,
        0.7556855,
        0.7586303636507689,
        0.76156384,
        0.7644860688461087,
        0.76739717,
        0.7702972738840048,
        0.7731865,
        0.7760649434180147,
        0.77893275,
        0.7817900775756758,
        0.784637,
        0.7874735905949481,
        0.7903,
        0.7928039417157309,
        0.7953,
        0.7978039170121942,
        0.8003,
        0.8028038926163724,
        0.8053,
        0.8078038685225517,
        0.8103,
        0.8128038447251588,
        0.8153
    ],
    "WeatherSettings": {
        "CLEAR": [
            "grass",
            "ground",
            "fire"
        ],
        "FOG": [
            "dark",
            "ghost"
        ],
        "CLOUDY": [
            "fairy",
            "fighting",
            "poison"
        ],
        "PARTLY_CLOUDY": [
            "normal",
            "rock"
        ],
        "RAINY": [
            "water",
            "electric",
            "bug"
        ],
        "SNOW": [
            "ice",
            "steel"
        ],
        "WINDY": [
            "dragon",
            "flying",
            "psychic"
        ]
    },
    "FriendAttackBonusMultipliers": [
        {
            "name": "FRIENDSHIP_LEVEL_0",
            "multiplier": 1.0
        },
        {
            "name": "FRIENDSHIP_LEVEL_1",
            "multiplier": 1.03
        },
        {
            "name": "FRIENDSHIP_LEVEL_2",
            "multiplier": 1.05
        },
        {
            "name": "FRIENDSHIP_LEVEL_3",
            "multiplier": 1.07
        },
        {
            "name": "FRIENDSHIP_LEVEL_4",
            "multiplier": 1.1
        }
    ],
    "TypeEffectiveness": {
        "bug": {
            "normal": 1.0,
            "fighting": 0.625,
            "flying": 0.625,
            "poison": 0.625,
            "ground": 1.0,
            "rock": 1.0,
            "bug": 1.0,
            "ghost": 0.625,
            "steel": 0.625,
            "fire": 0.625,
            "water": 1.0,
            "grass": 1.6,
            "electric": 1.0,
            "psychic": 1.6,
            "ice": 1.0,
            "dragon": 1.0,
            "dark": 1.6,
            "fairy": 0.625
        },
        "dark": {
            "normal": 1.0,
            "fighting": 0.625,
            "flying": 1.0,
            "poison": 1.0,
            "ground": 1.0,
            "rock": 1.0,
            "bug": 1.0,
            "ghost": 1.6,
            "steel": 1.0,
            "fire": 1.0,
            "water": 1.0,
            "grass": 1.0,
            "electric": 1.0,
            "psychic": 1.6,
            "ice": 1.0,
            "dragon": 1.0,
            "dark": 0.625,
            "fairy": 0.625
        },
        "dragon": {
            "normal": 1.0,
            "fighting": 1.0,
            "flying": 1.0,
            "poison": 1.0,
            "ground": 1.0,
            "rock": 1.0,
            "bug": 1.0,
            "ghost": 1.0,
            "steel": 0.625,
            "fire": 1.0,
            "water": 1.0,
            "grass": 1.0,
            "electric": 1.0,
            "psychic": 1.0,
            "ice": 1.0,
            "dragon": 1.6,
            "dark": 1.0,
            "fairy": 0.390625
        },
        "electric": {
            "normal": 1.0,
            "fighting": 1.0,
            "flying": 1.6,
            "poison": 1.0,
            "ground": 0.390625,
            "rock": 1.0,
            "bug": 1.0,
            "ghost": 1.0,
            "steel": 1.0,
            "fire": 1.0,
            "water": 1.6,
            "grass": 0.625,
            "electric": 0.625,
            "psychic": 1.0,
            "ice": 1.0,
            "dragon": 0.625,
            "dark": 1.0,
            "fairy": 1.0
        },
        "fairy": {
            "normal": 1.0,
            "fighting": 1.6,
            "flying": 1.0,
            "poison": 0.625,
            "ground": 1.0,
            "rock": 1.0,
            "bug": 1.0,
            "ghost": 1.0,
            "steel": 0.625,
            "fire": 0.625,
            "water": 1.0,
            "grass": 1.0,
            "electric": 1.0,
            "psychic": 1.0,
            "ice": 1.0,
            "dragon": 1.6,
            "dark": 1.6,
            "fairy": 1.0
        },
        "fighting": {
            "normal": 1.6,
            "fighting": 1.0,
            "flying": 0.625,
            "poison": 0.625,
            "ground": 1.0,
            "rock": 1.6,
            "bug": 0.625,
            "ghost": 0.390625,
            "steel": 1.6,
            "fire": 1.0,
            "water": 1.0,
            "grass": 1.0,
            "electric": 1.0,
            "psychic": 0.625,
            "ice": 1.6,
            "dragon": 1.0,
            "dark": 1.6,
            "fairy": 0.625
        },
        "fire": {
            "normal": 1.0,
            "fighting": 1.0,
            "flying": 1.0,
            "poison": 1.0,
            "ground": 1.0,
            "rock": 0.625,
            "bug": 1.6,
            "ghost": 1.0,
            "steel": 1.6,
            "fire": 0.625,
            "water": 0.625,
            "grass": 1.6,
            "electric": 1.0,
            "psychic": 1.0,
            "ice": 1.6,
            "dragon": 0.625,
            "dark": 1.0,
            "fairy": 1.0
        },
        "flying": {
            "normal": 1.0,
            "fighting": 1.6,
            "flying": 1.0,
            "poison": 1.0,
            "ground": 1.0,
            "rock": 0.625,
            "bug": 1.6,
            "ghost": 1.0,
            "steel": 0.625,
            "fire": 1.0,
            "water": 1.0,
            "grass": 1.6,
            "electric": 0.625,
            "psychic": 1.0,
            "ice": 1.0,
            "dragon": 1.0,
            "dark": 1.0,
            "fairy": 1.0
        },
        "ghost": {
            "normal": 0.390625,
            "fighting": 1.0,
            "flying": 1.0,
            "poison": 1.0,
            "ground": 1.0,
            "rock": 1.0,
            "bug": 1.0,
            "ghost": 1.6,
            "steel": 1.0,
            "fire": 1.0,
            "water": 1.0,
            "grass": 1.0,
            "electric": 1.0,
            "psychic": 1.6,
            "ice": 1.0,
            "dragon": 1.0,
            "dark": 0.625,
            "fairy": 1.0
        },
        "grass": {
            "normal": 1.0,
            "fighting": 1.0,
            "flying": 0.625,
            "poison": 0.625,
            "ground": 1.6,
            "rock": 1.6,
            "bug": 0.625,
            "ghost": 1.0,
            "steel": 0.625,
            "fire": 0.625,
            "water": 1.6,
            "grass": 0.625,
            "electric": 1.0,
            "psychic": 1.0,
            "ice": 1.0,
            "dragon": 0.625,
            "dark": 1.0,
            "fairy": 1.0
        },
        "ground": {
            "normal": 1.0,
            "fighting": 1.0,
            "flying": 0.390625,
            "poison": 1.6,
            "ground": 1.0,
            "rock": 1.6,
            "bug": 0.625,
            "ghost": 1.0,
            "steel": 1.6,
            "fire": 1.6,
            "water": 1.0,
            "grass": 0.625,
            "electric": 1.6,
            "psychic": 1.0,
            "ice": 1.0,
            "dragon": 1.0,
            "dark": 1.0,
            "fairy": 1.0
        },
        "ice": {
            "normal": 1.0,
            "fighting": 1.0,
            "flying": 1.6,
            "poison": 1.0,
            "ground": 1.6,
            "rock": 1.0,
            "bug": 1.0,
            "ghost": 1.0,
            "steel": 0.625,
            "fire": 0.625,
            "water": 0.625,
            "grass": 1.6,
            "electric": 1.0,
            "psychic": 1.0,
            "ice": 0.625,
            "dragon": 1.6,
            "dark": 1.0,
            "fairy": 1.0
        },
        "normal": {
            "normal": 1.0,
            "fighting": 1.0,
            "flying": 1.0,
            "poison": 1.0,
            "ground": 1.0,
            "rock": 0.625,
            "bug": 1.0,
            "ghost": 0.390625,
            "steel": 0.625,
            "fire": 1.0,
            "water": 1.0,
            "grass": 1.0,
            "electric": 1.0,
            "psychic": 1.0,
            "ice": 1.0,
            "dragon": 1.0,
            "dark": 1.0,
            "fairy": 1.0
        },
        "poison": {
            "normal": 1.0,
            "fighting": 1.0,
            "flying": 1.0,
            "poison": 0.625,
            "ground": 0.625,
            "rock": 0.625,
            "bug": 1.0,
            "ghost": 0.625,
            "steel": 0.390625,
            "fire": 1.0,
            "water": 1.0,
            "grass": 1.6,
            "electric": 1.0,
            "psychic": 1.0,
            "ice": 1.0,
            "dragon": 1.0,
            "dark": 1.0,
            "fairy": 1.6
        },
        "psychic": {
            "normal": 1.0,
            "fighting": 1.6,
            "flying": 1.0,
            "poison": 1.6,
            "ground": 1.0,
            "rock": 1.0,
            "bug": 1.0,
            "ghost": 1.0,
            "steel": 0.625,
            "fire": 1.0,
            "water": 1.0,
            "grass": 1.0,
            "electric": 1.0,
            "psychic": 0.625,
            "ice": 1.0,
            "dragon": 1.0,
            "dark": 0.390625,
            "fairy": 1.0
        },
        "rock": {
            "normal": 1.0,
            "fighting": 0.625,
            "flying": 1.6,
            "poison": 1.0,
            "ground": 0.625,
            "rock": 1.0,
            "bug": 1.6,
            "ghost": 1.0,
            "steel": 0.625,
            "fire": 1.6,
            "water": 1.0,
            "grass": 1.0,
            "electric": 1.0,
            "psychic": 1.0,
            "ice": 1.6,
            "dragon": 1.0,
            "dark": 1.0,
            "fairy": 1.0
        },
        "steel": {
            "normal": 1.0,
            "fighting": 1.0,
            "flying": 1.0,
            "poison": 1.0,
            "ground": 1.0,
            "rock": 1.6,
            "bug": 1.0,
            "ghost": 1.0,
            "steel": 0.625,
            "fire": 0.625,
            "water": 0.625,
            "grass": 1.0,
            "electric": 0.625,
            "psychic": 1.0,
            "ice": 1.6,
            "dragon": 1.0,
            "dark": 1.0,
            "fairy": 1.6
        },
        "water": {
            "normal": 1.0,
            "fighting": 1.0,
            "flying": 1.0,
            "poison": 1.0,
            "ground": 1.6,
            "rock": 1.6,
            "bug": 1.0,
            "ghost": 1.0,
            "steel": 1.0,
            "fire": 1.6,
            "water": 0.625,
            "grass": 0.625,
            "electric": 1.0,
            "psychic": 1.0,
            "ice": 1.0,
            "dragon": 0.625,
            "dark": 1.0,
            "fairy": 1.0
        }
    },
    "PvEBattleSettings": {
        "retargetSeconds": 0.5,
        "enemyAttackInterval": 1.5,
        "attackServerInterval": 5.0,
        "roundDurationSeconds": 99.0,
        "bonusTimePerAllySeconds": 10.0,
        "maximumAttackersPerBattle": 20,
        "sameTypeAttackBonusMultiplier": 1.2,
        "maximumEnergy": 100,
        "energyDeltaPerHealthLost": 0.5,
        "dodgeDurationMs": 500,
        "minimumPlayerLevel": 5,
        "swapDurationMs": 1000,
        "dodgeDamageReductionPercent": 0.75,
        "minimumRaidPlayerLevel": 5,
        "weatherAttackBonusMultiplier": 1.2
    },
    "PvPBattleSettings": {
        "roundDurationSeconds": 270.0,
        "turnDurationSeconds": 0.5,
        "minigameDurationSeconds": 7.0,
        "sameTypeAttackBonusMultiplier": 1.2,
        "fastAttackBonusMultiplier": 1.3,
        "chargeAttackBonusMultiplier": 1.3,
        "defenseBonusMultiplier": 1.0,
        "minigameBonusBaseMultiplier": 0.0001,
        "minigameBonusVariableMultiplier": 1.0,
        "maxEnergy": 100,
        "defenderMinigameMultiplier": 1.0,
        "changePokemonDurationSeconds": 12.0,
        "minigameSubmitScoreDurationSeconds": 10.0,
        "quickSwapCooldownDurationSeconds": 60.0,
        "chargeScoreBase": 0.25,
        "chargeScoreNice": 0.5,
        "chargeScoreGreat": 0.75,
        "chargeScoreExcellent": 1.0,
        "minimumStatStage": -4,
        "maximumStatStage": 4,
        "attackBuffMultiplier": [
            0.5,
            0.5714286,
            0.6666667,
            0.8,
            1.0,
            1.25,
            1.5,
            1.75,
            2.0
        ],
        "defenseBuffMultiplier": [
            0.5,
            0.5714286,
            0.6666667,
            0.8,
            1.0,
            1.25,
            1.5,
            1.75,
            2.0
        ]
    },
    "RaidTierSettings": [
        {
            "name": "1",
            "cpm": 0.6,
            "maxHP": 600,
            "timelimit": 180000
        },
        {
            "name": "2",
            "cpm": 0.67,
            "maxHP": 1800,
            "timelimit": 180000
        },
        {
            "name": "3",
            "cpm": 0.7300000190734863,
            "maxHP": 3600,
            "timelimit": 180000
        },
        {
            "name": "4",
            "cpm": 0.7900000214576721,
            "maxHP": 9000,
            "timelimit": 180000
        },
        {
            "name": "5",
            "cpm": 0.7900000214576721,
            "maxHP": 15000,
            "timelimit": 300000
        },
        {
            "name": "6",
            "cpm": 0.7900000214576721,
            "maxHP": 18750,
            "timelimit": 3000000
        }
    ]
}